sombra_engine/__init__.py
sombra_engine/animations/__init__.py
sombra_engine/animations/animation.py
sombra_engine/app/__init__.py
sombra_engine/app/app.py
sombra_engine/camera.py
sombra_engine/components/__init__.py
sombra_engine/constants/__init__.py
sombra_engine/constants/actions.py
sombra_engine/debug/__init__.py
sombra_engine/debug/gizmo.py
sombra_engine/debug/stats.py
sombra_engine/graphics/__init__.py
sombra_engine/graphics/material_group.py
sombra_engine/graphics/skeletal_material_group.py
sombra_engine/graphics/wireframe_group.py
sombra_engine/models/__init__.py
sombra_engine/models/mesh.py
sombra_engine/models/model.py
sombra_engine/models/obj/__init__.py
sombra_engine/models/obj/mtl_loader.py
sombra_engine/models/obj/mtl_parser.py
sombra_engine/models/obj/obj_loader.py
sombra_engine/models/obj/obj_parser.py
sombra_engine/models/skeletal_mesh.py
sombra_engine/models/wireframe.py
sombra_engine/primitives/__init__.py
sombra_engine/primitives/material.py
sombra_engine/primitives/scene_object.py
sombra_engine/primitives/transform.py
sombra_engine/primitives/triangle.py
sombra_engine/primitives/vertex.py
sombra_engine/primitives/vertex_group.py
sombra_engine/scene/__init__.py
sombra_engine/scene/cameras/__init__.py
sombra_engine/scene/cameras/camera.py
sombra_engine/scene/cameras/controllers.py
sombra_engine/scene/cameras/orthographic_camera.py
sombra_engine/scene/cameras/perspective_camera.py
sombra_engine/scene/lights.py
sombra_engine/scene/scene.py
sombra_engine/shaders/blinn.frag
sombra_engine/shaders/blinn_barycentric.frag
sombra_engine/shaders/default.vert
sombra_engine/shaders/gizmo.frag
sombra_engine/shaders/gizmo.vert
sombra_engine/shaders/lambert.frag
sombra_engine/shaders/normals.frag
sombra_engine/shaders/normals_from_bump.frag
sombra_engine/shaders/skeletal.vert
sombra_engine/shaders/solid.frag
sombra_engine/shaders/solid_textured.frag
sombra_engine/shaders/specular.frag
sombra_engine/shaders/wireframe.frag
sombra_engine/utils.py
sombra_engine-0.1.0.dist-info/WHEEL
sombra_engine-0.1.0.dist-info/METADATA
sombra_engine-0.1.0.dist-info/RECORD
