Metadata-Version: 2.4
Name: sombra-engine
Version: 0.1.0
Summary: Small 3D game engine used at Sombra Studio
Author: Jesus Henriquez
License-Expression: MIT
Classifier: Programming Language :: Python :: 3
Classifier: Operating System :: OS Independent
Classifier: Topic :: Games/Entertainment
Classifier: Topic :: Multimedia :: Graphics :: 3D Rendering
Requires-Dist: psutil==7.1.3
Requires-Dist: pudu-ui==0.1.2
Requires-Python: >=3.11
Project-URL: Homepage, https://github.com/sombra-studio/sombra-engine
Project-URL: Issues, https://github.com/sombra-studio/sombra-engine/issues
